Workbook

Sheet 1_Сводка
A1: Показатель | B1: Значение (₽) | C1: Доходы мес. (₽) | D1: Расходы мес. (₽) | E1: Комментарий / Статус
A2: Общий котел (кумулятивный остаток) | B2: =2_Операции!G26 -> 201200 | C2: 120000 | D2: 69100 | E2: Переходящий остаток с учетом августа и сентября
A3: Личный счет: Муж | B3: 49800 | C3: 28000 | D3: 3200 | E3: Свободный личный остаток мужа
A4: Личный счет: Жена | B4: 49900 | C4: 24000 | D4: 4100 | E4: Свободный личный остаток жены
A5: Потребительские расходы (Общий котел, Окт) | B5: 34100 | C5: 0 | D5: 34100 | E5: Без учета переводов в копилки и погашения кредитов
A6: Отложено в копилки и погашено кредитов (Окт) | B6: 35000 | C6: 0 | D6: 35000 | E6: Копилка Отпуск (15 000 ₽) + Автокредит (20 000 ₽)
A7: Резерв на неоплаченные обязательные счета (Окт) | B7: =4_Постоянные_счета!C8 -> 29350 | C7: 0 | D7: 0 | E7: Связь, интернет, детский сад и рассрочка
A8: Планируемые расходы месяца (по прошлым мес.) | B8: =3_План_и_Прогноз!G10 -> 104550 | C8: 0 | D8: 0 | E8: Прогноз на основе средних трат августа–сентября + счетов
A9: Всего накоплено в семейных копилках | B9: =5_Копилки_и_Долги!D5 -> 460000 | C9: 0 | D9: 0 | E9: 3 активные копилки (из 770 000 ₽ цели)
A10: Остаток по кредитам и рассрочкам | B10: =5_Копилки_и_Долги!D9 -> 0 | C10: 0 | D10: 0 | E10: Автокредит + Рассрочка на технику

Sheet 2_Операции
A1: ID | B1: Дата | C1: Месяц | D1: Тип | E1: Категория | F1: Название / Комментарий | G1: Сумма (₽) | H1: Счет | I1: Автор | J1: ID_Копилки | K1: ID_Долга | L1: ID_Регулярного
A2: 1 | B2: 2026-10-23 | C2: 2026-10 | D2: Расход | E2: Продукты | F2: Супермаркет (ВкусВилл) | G2: 25700 | H2: Общий котел | I2: Муж
A3: 2 | B3: 2026-10-23 | C3: 2026-10 | D3: Расход | E3: Кафе и еда вне дома | F3: Кофейня и выпечка | G3: 2200 | H3: Общий котел | I3: Жена
A4: 7 | B4: 2026-10-22 | C4: 2026-10 | D4: Расход | E4: Развлечения и кино | F4: Игры в Steam и гаджеты | G4: 3200 | H4: Личный | I4: Муж
A5: 9 | B5: 2026-10-21 | C5: 2026-10 | D5: Расход | E5: Шопинг и вещи | F5: Косметика и уход | G5: 4100 | H5: Личный | I5: Жена
A6: 3 | B6: 2026-10-20 | C6: 2026-10 | D6: Доход | E6: Зарплата | F6: Аванс по проекту (в общий бюджет) | G6: 120000 | H6: Общий котел | I6: Муж
A7: 6 | B7: 2026-10-19 | C7: 2026-10 | D7: Доход | E7: Подработка | F7: Фриланс (на личную карту) | G7: 28000 | H7: Личный | I7: Муж
A8: 4 | B8: 2026-10-18 | C8: 2026-10 | D8: Расход | E8: Дом и ЖКУ | F8: Оплата ЖКУ и капремонт | G8: 6200 | H8: Общий котел | I8: Жена | L8: rec_2
A9: 8 | B9: 2026-10-17 | C9: 2026-10 | D9: Доход | E9: Другое | F9: Премия и кешбэк (личный счет) | G9: 24000 | H9: Личный | I9: Жена
A10: 5 | B10: 2026-10-15 | C10: 2026-10 | D10: Расход | E10: Накопления | F10: В копилку: Отпуск в горах | G10: 15000 | H10: Общий котел | I10: Муж | J10: g1
A11: 10 | B11: 2026-10-12 | C11: 2026-10 | D11: Расход | E11: Долги и кредиты | F11: Платёж по автокредиту | G11: 20000 | H11: Общий котел | I11: Муж | K11: debt_1
A12: sep9 | B12: 2026-09-26 | C12: 2026-09 | D12: Расход | E12: Транспорт и авто | F12: Заправка и парковка | G12: 5200 | H12: Общий котел | I12: Муж
A13: sep5 | B13: 2026-09-25 | C13: 2026-09 | D13: Расход | E13: Накопления | F13: В копилку: Отпуск в горах | G13: 20000 | H13: Общий котел | I13: Муж | J13: g1
A14: sep8 | B14: 2026-09-22 | C14: 2026-09 | D14: Доход | E14: Другое | F14: Премия жены | G14: 30000 | H14: Личный | I14: Жена
A15: sep4 | B15: 2026-09-21 | C15: 2026-09 | D15: Расход | E15: Кафе и еда вне дома | F15: Кофейни и рестораны | G15: 3800 | H15: Общий котел | I15: Жена
A16: sep7 | B16: 2026-09-20 | C16: 2026-09 | D16: Доход | E16: Подработка | F16: Фриланс мужа | G16: 35000 | H16: Личный | I16: Муж
A17: sep3 | B17: 2026-09-18 | C17: 2026-09 | D17: Расход | E17: Дом и ЖКУ | F17: ЖКУ и интернет | G17: 5900 | H17: Общий котел | I17: Жена
A18: sep2 | B18: 2026-09-14 | C18: 2026-09 | D18: Расход | E18: Продукты | F18: Супермаркет (ВкусВилл) | G18: 21500 | H18: Общий котел | I18: Муж
A19: sep6 | B19: 2026-09-12 | C19: 2026-09 | D19: Расход | E19: Долги и кредиты | F19: Платёж по автокредиту | G19: 20000 | H19: Общий котел | I19: Муж | K19: debt_1
A20: sep1 | B20: 2026-09-10 | C20: 2026-09 | D20: Доход | E20: Зарплата | F20: Зарплата (сентябрь) | G20: 135000 | H20: Общий котел | I20: Муж
A21: aug5 | B21: 2026-08-24 | C21: 2026-08 | D21: Расход | E21: Транспорт и авто | F21: Бензин и ТО | G21: 4800 | H21: Общий котел | I21: Муж
A22: aug4 | B22: 2026-08-22 | C22: 2026-08 | D22: Расход | E22: Кафе и еда вне дома | F22: Кафе и ужины | G22: 4200 | H22: Общий котел | I22: Жена
A23: aug3 | B23: 2026-08-18 | C23: 2026-08 | D23: Расход | E23: Дом и ЖКУ | F23: ЖКУ, свет и вода | G23: 5800 | H23: Общий котел | I23: Жена
A24: aug2 | B24: 2026-08-15 | C24: 2026-08 | D24: Расход | E24: Продукты | F24: Супермаркеты и фермерская лавка | G24: 23500 | H24: Общий котел | I24: Муж
A25: aug1 | B25: 2026-08-10 | C25: 2026-08 | D25: Доход | E25: Зарплата | F25: Зарплата (август) | G25: 130000 | H25: Общий котел | I25: Муж
A26: ИТОГО | D26: Баланс Общего котла | G26: =SUMIFS(G2:G25,D2:D25,"Доход",H2:H25,"Общий котел")-SUMIFS(G2:G25,D2:D25,"Расход",H2:H25,"Общий котел") -> 201200

Sheet 3_План_и_Прогноз
A1: Категория | B1: Корзина 50/30/20 | C1: Прошлый мес. (₽) | D1: Среднее за прошл. мес. (₽) | E1: Постоянные счета (₽) | F1: Авто-прогноз (₽) | G1: План на месяц (₽) | H1: Факт октября (₽) | I1: Остаток плана (₽) | J1: Статус
A2: Дом и ЖКУ | B2: База (50%) | C2: 5900 | D2: 5850 | E2: 51200 | F2: =MAX(D2,E2) -> 51200 | G2: =F2 -> 51200 | H2: 6200 | I2: =G2-H2 -> 45000 | J2: =IF(H2>G2,"Превышение","В рамках плана") -> В рамках плана
A3: Продукты | B3: База (50%) | C3: 21500 | D3: 22500 | E3: 0 | F3: =MAX(D3,E3) -> 22500 | G3: =F3 -> 22500 | H3: 25700 | I3: =G3-H3 -> -3200 | J3: =IF(H3>G3,"Превышение","В рамках плана") -> Превышение
A4: Дети и секции | B4: База (50%) | C4: 0 | D4: 0 | E4: 12000 | F4: =MAX(D4,E4) -> 12000 | G4: =F4 -> 12000 | H4: 0 | I4: =G4-H4 -> 12000 | J4: =IF(H4>G4,"Превышение","В рамках плана") -> В рамках плана
A5: Транспорт и авто | B5: База (50%) | C5: 5200 | D5: 5000 | E5: 0 | F5: =MAX(D5,E5) -> 5000 | G5: =F5 -> 5000 | H5: 0 | I5: =G5-H5 -> 5000 | J5: =IF(H5>G5,"Превышение","В рамках плана") -> В рамках плана
A6: Кафе и еда вне дома | B6: Хотелки (30%) | C6: 3800 | D6: 4000 | E6: 0 | F6: =MAX(D6,E6) -> 4000 | G6: =F6 -> 4000 | H6: 2200 | I6: =G6-H6 -> 1800 | J6: =IF(H6>G6,"Превышение","В рамках плана") -> В рамках плана
A7: Связь и интернет | B7: База (50%) | C7: 0 | D7: 0 | E7: 2350 | F7: =MAX(D7,E7) -> 2350 | G7: =F7 -> 2350 | H7: 0 | I7: =G7-H7 -> 2350 | J7: =IF(H7>G7,"Превышение","В рамках плана") -> В рамках плана
A8: Шопинг и вещи | B8: Хотелки (30%) | C8: 0 | D8: 0 | E8: 0 | F8: 4000 | G8: 4000 | H8: 4100 | I8: =G8-H8 -> -100 | J8: =IF(H8>G8,"Превышение","В рамках плана") -> Превышение
A9: Развлечения и кино | B9: Хотелки (30%) | C9: 0 | D9: 0 | E9: 0 | F9: 3500 | G9: 3500 | H9: 3200 | I9: =G9-H9 -> 300 | J9: =IF(H9>G9,"Превышение","В рамках плана") -> В рамках плана
A10: ИТОГО ПЛАН / ФАКТ | C10: =SUM(C2:C9) -> 36400 | D10: =SUM(D2:D9) -> 37350 | E10: =SUM(E2:E9) -> 65550 | F10: =SUM(F2:F9) -> 104550 | G10: =SUM(G2:G9) -> 104550 | H10: =SUM(H2:H9) -> 41400 | I10: =SUM(I2:I9) -> 63150

Sheet 4_Постоянные_счета
A1: ID | B1: Название постоянного расхода | C1: Плановая сумма (₽) | D1: День оплаты | E1: Категория | F1: Счет | G1: Ответственный | H1: Обязательный | I1: Статус в октябре 2026
A2: rec_1 | B2: Аренда / Ипотека | C2: 45000 | D2: 5 | E2: Дом и ЖКУ | F2: Общий котел | G2: Муж | H2: Да | I2: Оплачено
A3: rec_2 | B3: ЖКУ и капремонт | C3: 6200 | D3: 15 | E3: Дом и ЖКУ | F3: Общий котел | G3: Жена | H3: Да | I3: Оплачено
A4: rec_3 | B4: Домашний интернет и ТВ | C4: 950 | D4: 25 | E4: Связь и интернет | F4: Общий котел | G4: Муж | H4: Да | I4: Ожидает оплаты
A5: rec_5 | B5: Мобильная связь (2 номера) | C5: 1400 | D5: 27 | E5: Связь и интернет | F5: Общий котел | G5: Жена | H5: Да | I5: Ожидает оплаты
A6: rec_4 | B6: Детский сад / Секции | C6: 12000 | D6: 28 | E6: Дети и секции | F6: Общий котел | G6: Жена | H6: Да | I6: Ожидает оплаты
B7: ИТОГО ПОСТОЯННЫХ СЧЕТОВ В МЕСЯЦ | C7: =SUM(C2:C6) -> 65550
B8: ОСТАЛОСЬ ОПЛАТИТЬ В ОКТЯБРЕ (РЕЗЕРВ) | C8: =SUMIFS(C2:C6,I2:I6,"Ожидает оплаты")+15000 -> 29350 | I8: Включая рассрочку 15 000 ₽

Sheet 5_Копилки_и_Долги
A1: Тип | B1: ID | C1: Название | D1: Текущее / Остаток (₽) | E1: Цель / Начальная сумма (₽) | F1: Ежемесячный платеж (₽) | G1: День платежа | H1: Прогресс (%)
A2: Копилка | B2: g1 | C2: Отпуск в горах | D2: 85000 | E2: 200000 | F2: 0 | H2: =D2/E2 -> 0.425
A3: Копилка | B3: g2 | C3: Подушка безопасности | D3: 310000 | E3: 450000 | F3: 0 | H3: =D3/E3 -> 0.68888889
A4: Копилка | B4: g3 | C4: Апгрейд рабочего места | D4: 65000 | E4: 120000 | F4: 0 | H4: =D4/E4 -> 0.54166667
A5: ИТОГО КОПИЛКИ | C5: Всего накоплено | D5: =SUM(D2:D4) -> 460000 | E5: =SUM(E2:E4) -> 770000 | F5: 0 | H5: =D5/E5 -> 0.5974026
A6: Кредит/Долг | B6: debt_1 | C6: Автокредит | D6: 240000 | E6: 600000 | F6: 20000 | G6: 12 | H6: =(E6-D6)/E6 -> 0.6
A7: Кредит/Долг | B7: debt_2 | C7: Рассрочка на технику | D7: 30000 | E7: 90000 | F7: 15000 | G7: 26 | H7: =(E7-D7)/E7 -> 0.66666667
A8: ИТОГО ДОЛГИ | C8: Всего остаток долгов | D8: =SUM(D6:D7) -> 270000 | E8: =SUM(E6:E7) -> 690000 | F8: =SUM(F6:F7) -> 35000 | H8: =(E8-D8)/E8 -> 0.60869565
